{
  "elements": [
    {
      "element": {
        "element_type": "minecraft:empty_pool_element"
      },
      "weight": 50
    },
    {
      "element": {
        "element_type": "minecraft:single_pool_element",
        "location": "minecraft:trial_chambers/reward/wind_pot",
        "processors": {
          "processors": []
        },
        "projection": "rigid"
      },
      "weight": 11
    },
    {
      "element": {
        "element_type": "minecraft:single_pool_element",
        "location": "minecraft:trial_chambers/reward/redstone_pot",
        "processors": {
          "processors": []
        },
        "projection": "rigid"
      },
      "weight": 4
    },
    {
      "element": {
        "element_type": "minecraft:single_pool_element",
        "location": "minecraft:trial_chambers/reward/lapis_pot",
        "processors": {
          "processors": []
        },
        "projection": "rigid"
      },
      "weight": 4
    },
    {
      "element": {
        "element_type": "minecraft:single_pool_element",
        "location": "minecraft:trial_chambers/reward/coal_pot",
        "processors": {
          "processors": []
        },
        "projection": "rigid"
      },
      "weight": 4
    },
    {
      "element": {
        "element_type": "minecraft:single_pool_element",
        "location": "minecraft:trial_chambers/reward/copper_pot",
        "processors": {
          "processors": []
        },
        "projection": "rigid"
      },
      "weight": 4
    },
    {
      "element": {
        "element_type": "minecraft:single_pool_element",
        "location": "minecraft:trial_chambers/reward/amethyst_pot",
        "processors": {
          "processors": []
        },
        "projection": "rigid"
      },
      "weight": 4
    },
    {
      "element": {
        "element_type": "minecraft:single_pool_element",
        "location": "minecraft:trial_chambers/reward/pot_pot",
        "processors": {
          "processors": []
        },
        "projection": "rigid"
      },
      "weight": 2
    }
  ],
  "fallback": "minecraft:empty"
}